os_net_config/__init__.py
os_net_config/cli.py
os_net_config/common.py
os_net_config/dcb_config.py
os_net_config/dcb_netlink.py
os_net_config/impl_eni.py
os_net_config/impl_ifcfg.py
os_net_config/impl_iproute.py
os_net_config/impl_nmstate.py
os_net_config/objects.py
os_net_config/schema.yaml
os_net_config/sriov_bind_config.py
os_net_config/sriov_config.py
os_net_config/utils.py
os_net_config/validator.py
os_net_config/version.py
os_net_config/tests/__init__.py
os_net_config/tests/base.py
os_net_config/tests/test_cli.py
os_net_config/tests/test_impl_eni.py
os_net_config/tests/test_impl_ifcfg.py
os_net_config/tests/test_impl_nmstate.py
os_net_config/tests/test_objects.py
os_net_config/tests/test_os_net_config.py
os_net_config/tests/test_sriov_bind_config.py
os_net_config/tests/test_sriov_config.py
os_net_config/tests/test_utils.py
os_net_config/tests/test_validator.py
os_net_config/tests/environment/netinfo_running_info_1.yaml
os_net_config-17.0.0.dist-info/AUTHORS
os_net_config-17.0.0.dist-info/LICENSE
os_net_config-17.0.0.dist-info/METADATA
os_net_config-17.0.0.dist-info/WHEEL
os_net_config-17.0.0.dist-info/entry_points.txt
os_net_config-17.0.0.dist-info/pbr.json
os_net_config-17.0.0.dist-info/top_level.txt
os_net_config-17.0.0.dist-info/RECORD
