Metadata-Version: 2.1
Name: os-net-config
Version: 17.0.0
Summary: OpenStack network configuration
Home-page: https://opendev.org/openstack/os-net-config
Author: OpenStack
Author-email: openstack-discuss@lists.openstack.org
License: Apache License (2.0)
Classifier: Environment :: OpenStack
Classifier: Intended Audience :: Developers
Classifier: Intended Audience :: System Administrators
Classifier: License :: OSI Approved :: Apache Software License
Classifier: Operating System :: OS Independent
Classifier: Programming Language :: Python
Classifier: Programming Language :: Python :: Implementation :: CPython
Classifier: Programming Language :: Python :: 3 :: Only
Classifier: Programming Language :: Python :: 3
Classifier: Programming Language :: Python :: 3.8
Classifier: Programming Language :: Python :: 3.9
License-File: LICENSE
License-File: AUTHORS
Requires-Dist: pbr !=2.1.0,>=2.0.0
Requires-Dist: netaddr >=0.7.13
Requires-Dist: oslo.concurrency >=3.26.0
Requires-Dist: oslo.utils >=3.33.0
Requires-Dist: PyYAML >=3.10.0
Requires-Dist: jsonschema >=3.2.0
Requires-Dist: pyudev >=0.16.1
Requires-Dist: pyroute2 >=0.7.10
